diecast/__init__.py
diecast/component.py
diecast/inject.py
diecast/registry.py
diecast/types.py
diecast-0.3.2.dist-info/LICENSE
diecast-0.3.2.dist-info/WHEEL
diecast-0.3.2.dist-info/METADATA
diecast-0.3.2.dist-info/RECORD
